katie/__init__.py
katie/rl/__init__.py
katie/rl/replay_memory.py
katie/rl/softmax_body.py
katie/rl/tests/__init__.py
katie/rl/tests/replay_memory_serialization_test.py
katie/rl/tests/replay_memory_test.py
katie/rl/tests/softmax_body_test.py
ai_katie-0.1.2.dist-info/LICENSE
ai_katie-0.1.2.dist-info/METADATA
ai_katie-0.1.2.dist-info/WHEEL
ai_katie-0.1.2.dist-info/top_level.txt
ai_katie-0.1.2.dist-info/RECORD
