Metadata-Version: 2.1
Name: ai-katie
Version: 0.1.2
Summary: Utility things for Data Science and AI
Home-page: https://github.com/danpeczek/ai-katie
Author: danpeczek
Author-email: danpeczek@gmail.com
License: UNKNOWN
Project-URL: Bug Tracker, https://github.com/danpeczek/ai-katie/issues
Platform: UNKNOWN
Classifier: Intended Audience :: Developers
Classifier: Intended Audience :: Education
Classifier: Intended Audience :: Science/Research
Classifier: Operating System :: OS Independent
Classifier: Programming Language :: Python :: 3
Classifier: Programming Language :: Python :: 3.6
Classifier: Programming Language :: Python :: 3.7
Classifier: Programming Language :: Python :: 3.8
Classifier: Programming Language :: Python :: 3.9
Classifier: Topic :: Communications :: Email
Classifier: Topic :: Scientific/Engineering :: Artificial Intelligence
Classifier: Topic :: Scientific/Engineering :: Information Analysis
Requires-Python: >=3.6
License-File: LICENSE
Requires-Dist: torch
Requires-Dist: numpy
